{
	"title": "Resource Access",
	"description": "JSON schema for a ResourceAccess POJO",
	"name": "ResourceAccess",
	"properties": {
		"principalId": {
			"type": "integer",
			"description": "The id of the principal who is granted access"
		},
		"accessType": {
			"type": "array",
			"uniqueItems": true,
			"items": {
				"type": "object",
				"description": "The status of this URL",
				"name": "ACCESS_TYPE",
				"$ref": "org.sagebionetworks.repo.model.ACCESS_TYPE"
			}
		}
	}
}