{
    "description": "File record for file upload and download events",
    "properties": {
        "userId": {
            "type": "integer",
            "description": "The Id of user who initiated the file event."
        },
        "timestamp": {
            "type": "integer",
            "description": "The timestamp of the record, in UTC milliseconds"
        },
        "projectId": {
            "type": "integer",
            "description": "The project Id of file."
        },
        "fileHandleId": {
            "type": "string",
            "description": "The filehandle Id of file."
        },
        "associateType": {
            "$ref": "org.sagebionetworks.repo.model.file.FileHandleAssociateType",
            "description": "The association type of filehandle."
        },
        "associateId": {
            "type": "string",
            "description": "The association Id of filehandle."
        },
        "stack": {
            "type": "string",
            "description": "The stack number."
        },
        "instance": {
            "type": "string",
            "description": "The instance number."
        }
    }
}