<!DOCTYPE ui:UiBinder SYSTEM "http://dl.google.com/gwt/DTD/xhtml.ent">
<ui:UiBinder xmlns:ui="urn:ui:com.google.gwt.uibinder"
	xmlns:g="urn:import:com.google.gwt.user.client.ui" 
	xmlns:c="urn:import:com.google.gwt.user.cellview.client"
	xmlns:s="urn:import:org.sagebionetworks.web.client.view">
		
	<ui:style>
	</ui:style>	
	<g:HTMLPanel>

	<!-- start header -->
		<div id="container" class="clearfix">		
			<g:SimplePanel ui:field="header" />
			<div id="main" role="main">
	<!-- end header -->

			<div id="main_content" class="clearfix">
				<h2>Register With Synapse </h2>				
				<g:SimplePanel ui:field="registerAccountPanel" />
				<span ui:field="contentHtml"></span>
				<p>&nbsp;</p>
				<p>&nbsp;</p>
				<p>&nbsp;</p>
				<p>&nbsp;</p>
				<p>&nbsp;</p>
				<p>&nbsp;</p>
				<p>&nbsp;</p>
			</div>

<!-- start footer -->
				<g:SimplePanel ui:field="footer" />
			</div> <!-- id: main -->				
		</div> <!-- id: container -->
<!-- end footer -->

	</g:HTMLPanel>
</ui:UiBinder> 